wkdict/__init__.py
wkdict/command.py
wkdict/constants.py
wkdict/wkdict.py
wkdict-0.1.0.dist-info/LICENSE
wkdict-0.1.0.dist-info/METADATA
wkdict-0.1.0.dist-info/WHEEL
wkdict-0.1.0.dist-info/entry_points.txt
wkdict-0.1.0.dist-info/top_level.txt
wkdict-0.1.0.dist-info/RECORD
