Metadata-Version: 2.1
Name: wkdict
Version: 0.1.0
Summary: A dictionary app sits in your CLI environment
Home-page: https://github.com/jiaowoshabi/wkdict
Author: Wenhao Zhang
Author-email: wenhaoz@ucla.edu
License: UNKNOWN
Platform: UNKNOWN
Classifier: Programming Language :: Python :: 3
Classifier: License :: OSI Approved :: GNU General Public License v3 (GPLv3)
Classifier: Operating System :: OS Independent
Requires-Dist: click
Requires-Dist: requests
Requires-Dist: wiktionaryparser
